ocr_file_name_changer/__init__.py
ocr_file_name_changer/exceptions.py
ocr_file_name_changer/files_handling.py
ocr_file_name_changer/main.py
ocr_file_name_changer/ocr_handling.py
OCR_file_name_changer-1.0.2.dist-info/METADATA
OCR_file_name_changer-1.0.2.dist-info/WHEEL
OCR_file_name_changer-1.0.2.dist-info/entry_points.txt
OCR_file_name_changer-1.0.2.dist-info/top_level.txt
OCR_file_name_changer-1.0.2.dist-info/RECORD
